suitcase/utils/__init__.py
suitcase/utils/_version.py
suitcase/utils/tests/__init__.py
suitcase/utils/tests/conftest.py
suitcase/utils/tests/tests.py
suitcase_utils-0.5.4.dist-info/LICENSE
suitcase_utils-0.5.4.dist-info/METADATA
suitcase_utils-0.5.4.dist-info/WHEEL
suitcase_utils-0.5.4.dist-info/entry_points.txt
suitcase_utils-0.5.4.dist-info/top_level.txt
suitcase_utils-0.5.4.dist-info/RECORD
