Metadata-Version: 2.1
Name: suitcase-utils
Version: 0.5.4
Summary: UNKNOWN
Home-page: UNKNOWN
License: BSD (3-clause)
Platform: UNKNOWN
Classifier: Development Status :: 2 - Pre-Alpha
Classifier: Natural Language :: English
Classifier: Programming Language :: Python :: 3.6
Provides-Extra: test_fixtures
Provides-Extra: complete
